{
	"name": "DecelBut",
	"plugin-id": "Sprite",
	"sid": 320084219484302,
	"isGlobal": false,
	"instanceVariables": [],
	"behaviorTypes": [],
	"effectTypes": [],
	"animations": {
		"items": [
			{
				"frames": [
					{
						"width": 128,
						"height": 128,
						"originX": 0.5,
						"originY": 0.5,
						"originalSource": "",
						"exportFormat": "png",
						"exportQuality": 0.8,
						"imageSpriteId": 2590438,
						"useCollisionPoly": true,
						"duration": 1
					}
				],
				"sid": 616245575554187,
				"name": "Animation 1",
				"isLooping": false,
				"isPingPong": false,
				"repeatCount": 1,
				"repeatTo": 0,
				"speed": 5
			}
		],
		"subfolders": []
	}
}