{
	"name": "garage_switch",
	"plugin-id": "Sprite",
	"sid": 703629331964764,
	"isGlobal": false,
	"instanceVariables": [
		{
			"name": "direction",
			"type": "number",
			"desc": "",
			"sid": 635244465716351
		}
	],
	"behaviorTypes": [],
	"effectTypes": [],
	"animations": {
		"items": [
			{
				"frames": [
					{
						"width": 268,
						"height": 144,
						"originX": 0.5,
						"originY": 0.5,
						"originalSource": "",
						"exportFormat": "png",
						"exportQuality": 0.8,
						"imageSpriteId": 7962514,
						"collisionPoly": {
							"points": [
								1,
								0.5,
								1,
								0.9953703703703703,
								0.5,
								0.9953703703703703,
								0.0024875621890547706,
								0.9953703703703703,
								0.11940298507462688,
								0.5,
								0.16417910447761197,
								0.30092592592592593,
								0.5,
								0.037037037037037035,
								0.9975124378109452,
								0.004629629629629629
							]
						},
						"useCollisionPoly": true,
						"duration": 1
					}
				],
				"sid": 273911108043456,
				"name": "Animation 1",
				"isLooping": false,
				"isPingPong": false,
				"repeatCount": 1,
				"repeatTo": 0,
				"speed": 5
			}
		],
		"subfolders": []
	}
}